applipy_newrelic/__init__.py
applipy_newrelic/loghandler.py
applipy_newrelic/module.py
applipy_newrelic/version.py
applipy_newrelic-0.3.0.dist-info/LICENSE
applipy_newrelic-0.3.0.dist-info/METADATA
applipy_newrelic-0.3.0.dist-info/WHEEL
applipy_newrelic-0.3.0.dist-info/top_level.txt
applipy_newrelic-0.3.0.dist-info/RECORD
