Metadata-Version: 2.1
Name: applipy-newrelic
Version: 0.3.0
Summary: Publishes applipy metrics and logs to newrelic
Home-page: https://gitlab.com/applipy/applipy_newrelic
Author: Alessio Linares
Author-email: mail@alessio.cc
License: Apache 2.0
Project-URL: Source, https://gitlab.com/applipy/applipy_newrelic
Platform: UNKNOWN
Classifier: Development Status :: 5 - Production/Stable
Classifier: Intended Audience :: Developers
Classifier: License :: OSI Approved :: Apache Software License
Classifier: Programming Language :: Python :: 3.6
Classifier: Programming Language :: Python :: 3.7
Classifier: Programming Language :: Python :: 3.8
Classifier: Topic :: Software Development :: Libraries
Requires-Python: >=3.6
Requires-Dist: applipy-metrics (<2.0.0,>=1.2.0)
Requires-Dist: applipy-inject (<2.0.0,>=1.1.0)
Requires-Dist: applipy (>=1.0.0)
Requires-Dist: newrelic-telemetry-sdk (==0.4.2)
